{
  "parent": "minecraft:recipes/root",
  "rewards": {
    "recipes": [
      "abverticaledition:waxed_cut_copper_vertical_stair"
    ]
  },
  "criteria": {
    "has_item": {
      "trigger": "minecraft:inventory_changed",
      "conditions": {
        "items": [
          {
            "items": [
              "minecraft:waxed_cut_copper"
            ]
          }
        ]
      }
    },
    "has_the_recipe": {
      "trigger": "minecraft:recipe_unlocked",
      "conditions": {
        "recipe": "abverticaledition:waxed_cut_copper_vertical_stair"
      }
    }
  },
  "requirements": [
    [
      "has_item",
      "has_the_recipe"
    ]
  ]
}